<0>
    <ip>72.195.34.59</ip>
    <port>4145</port>
    <country>United States of America</country>
    <type>socks4</type>
    <anonymity>High</anonymity>
</0>
<1>
    <ip>142.54.229.249</ip>
    <port>4145</port>
    <country>United States of America</country>
    <type>socks4</type>
    <anonymity>High</anonymity>
</1>
<2>
    <ip>96.126.118.190</ip>
    <port>801</port>
    <country>United States of America</country>
    <type>socks4</type>
    <anonymity>High</anonymity>
</2>
<3>
    <ip>202.86.138.18</ip>
    <port>8080</port>
    <country>Macao</country>
    <type>socks4</type>
    <anonymity>High</anonymity>
</3>
<4>
    <ip>70.32.26.101</ip>
    <port>46394</port>
    <country>United States of America</country>
    <type>socks4</type>
    <anonymity>High</anonymity>
</4>
<5>
    <ip>184.178.172.5</ip>
    <port>15303</port>
    <country>United States of America</country>
    <type>socks4</type>
    <anonymity>High</anonymity>
</5>
<6>
    <ip>47.88.11.3</ip>
    <port>8082</port>
    <country>United States of America</country>
    <type>socks4</type>
    <anonymity>High</anonymity>
</6>
<7>
    <country>Brazil</country>
    <ip>170.254.255.252</ip>
    <port>45816</port>
    <type>socks4</type>
    <anonymity>elite</anonymity>
</7>
<8>
    <country>Brazil</country>
    <ip>177.38.5.215</ip>
    <port>4153</port>
    <type>socks4</type>
    <anonymity>elite</anonymity>
</8>
<9>
    <country>France</country>
    <ip>51.68.87.73</ip>
    <port>45177</port>
    <type>socks4</type>
    <anonymity>elite</anonymity>
</9>
<10>
    <country>Argentina</country>
    <ip>181.111.175.234</ip>
    <port>4153</port>
    <type>socks4</type>
    <anonymity>elite</anonymity>
</10>
<11>
    <country>Ukraine</country>
    <ip>195.149.125.91</ip>
    <port>1080</port>
    <type>socks4</type>
    <anonymity>elite</anonymity>
</11>
<12>
    <country>Burkina Faso</country>
    <ip>41.223.232.34</ip>
    <port>4145</port>
    <type>socks4</type>
    <anonymity>elite</anonymity>
</12>
<13>
    <country>Albania</country>
    <ip>185.89.156.130</ip>
    <port>5678</port>
    <type>socks4</type>
    <anonymity>elite</anonymity>
</13>
<14>
    <country>Korea, Republic of</country>
    <ip>147.47.224.168</ip>
    <port>1080</port>
    <type>socks4</type>
    <anonymity>elite</anonymity>
</14>
<15>
    <country>Netherlands</country>
    <ip>178.62.227.85</ip>
    <port>49650</port>
    <type>socks4</type>
    <anonymity>elite</anonymity>
</15>
<16>
    <country>China</country>
    <ip>113.103.52.2</ip>
    <port>38801</port>
    <type>socks4</type>
    <anonymity>elite</anonymity>
</16>
<17>
    <country>Iran, Islamic Republic of</country>
    <ip>94.139.169.250</ip>
    <port>5678</port>
    <type>socks4</type>
    <anonymity>elite</anonymity>
</17>
<18>
    <country>Argentina</country>
    <ip>200.0.247.86</ip>
    <port>4153</port>
    <type>socks4</type>
    <anonymity>elite</anonymity>
</18>
<19>
    <country>Cyprus</country>
    <ip>203.22.223.47</ip>
    <port>80</port>
    <type>socks4</type>
    <anonymity>elite</anonymity>
</19>
<20>
    <country>Brazil</country>
    <ip>177.38.5.224</ip>
    <port>4153</port>
    <type>socks4</type>
    <anonymity>elite</anonymity>
</20>
<21>
    <country>Thailand</country>
    <ip>119.42.110.113</ip>
    <port>4145</port>
    <type>socks4</type>
    <anonymity>elite</anonymity>
</21>
<22>
    <country>Poland</country>
    <ip>46.227.36.1</ip>
    <port>1088</port>
    <type>socks4</type>
    <anonymity>elite</anonymity>
</22>
<23>
    <country>Thailand</country>
    <ip>183.89.117.134</ip>
    <port>4145</port>
    <type>socks4</type>
    <anonymity>elite</anonymity>
</23>
<24>
    <country>Ecuador</country>
    <ip>186.47.82.62</ip>
    <port>53523</port>
    <type>socks4</type>
    <anonymity>elite</anonymity>
</24>
<25>
    <country>Bosnia and Herzegovina</country>
    <ip>5.59.163.102</ip>
    <port>5678</port>
    <type>socks4</type>
    <anonymity>elite</anonymity>
</25>
<26>
    <country>United States of America</country>
    <ip>45.196.151.73</ip>
    <port>5432</port>
    <type>socks4</type>
    <anonymity>elite</anonymity>
</26>
<27>
    <country>United States of America</country>
    <ip>98.206.244.30</ip>
    <port>18301</port>
    <type>socks4</type>
    <anonymity>elite</anonymity>
</27>
<28>
    <country>Germany</country>
    <ip>51.195.40.191</ip>
    <port>8804</port>
    <type>socks4</type>
    <anonymity>elite</anonymity>
</28>
<29>
    <country>United States of America</country>
    <ip>172.67.250.212</ip>
    <port>80</port>
    <type>socks4</type>
    <anonymity>elite</anonymity>
</29>
<30>
    <country>United States of America</country>
    <ip>68.183.111.115</ip>
    <port>13428</port>
    <type>socks4</type>
    <anonymity>elite</anonymity>
</30>
<31>
    <country>United States of America</country>
    <ip>208.113.155.176</ip>
    <port>12886</port>
    <type>socks4</type>
    <anonymity>elite</anonymity>
</31>
<32>
    <country>Indonesia</country>
    <ip>103.79.96.173</ip>
    <port>4153</port>
    <type>socks4</type>
    <anonymity>elite</anonymity>
</32>
<33>
    <country>Kenya</country>
    <ip>41.60.235.118</ip>
    <port>5678</port>
    <type>socks4</type>
    <anonymity>elite</anonymity>
</33>
<34>
    <country>Honduras</country>
    <ip>190.107.146.156</ip>
    <port>4145</port>
    <type>socks4</type>
    <anonymity>elite</anonymity>
</34>
<35>
    <country>Russian Federation</country>
    <ip>78.37.27.139</ip>
    <port>56228</port>
    <type>socks4</type>
    <anonymity>elite</anonymity>
</35>
<36>
    <country>South Africa</country>
    <ip>197.245.189.194</ip>
    <port>5678</port>
    <type>socks4</type>
    <anonymity>elite</anonymity>
</36>
<37>
    <country>Sweden</country>
    <ip>213.89.48.95</ip>
    <port>1080</port>
    <type>socks4</type>
    <anonymity>elite</anonymity>
</37>
<38>
    <country>India</country>
    <ip>103.211.8.201</ip>
    <port>52616</port>
    <type>socks4</type>
    <anonymity>elite</anonymity>
</38>
<39>
    <country>Seychelles</country>
    <ip>197.234.13.69</ip>
    <port>4145</port>
    <type>socks4</type>
    <anonymity>elite</anonymity>
</39>
<40>
    <country>United States of America</country>
    <ip>104.18.65.115</ip>
    <port>2105</port>
    <type>socks4</type>
    <anonymity>elite</anonymity>
</40>
<41>
    <country>India</country>
    <ip>103.47.93.202</ip>
    <port>1080</port>
    <type>socks4</type>
    <anonymity>elite</anonymity>
</41>
<42>
    <country>Thailand</country>
    <ip>14.207.123.29</ip>
    <port>8080</port>
    <type>socks4</type>
    <anonymity>elite</anonymity>
</42>
<43>
    <country>India</country>
    <ip>103.69.20.38</ip>
    <port>4145</port>
    <type>socks4</type>
    <anonymity>elite</anonymity>
</43>
<44>
    <country>Bangladesh</country>
    <ip>103.26.247.102</ip>
    <port>56707</port>
    <type>socks4</type>
    <anonymity>elite</anonymity>
</44>
<45>
    <country>Indonesia</country>
    <ip>202.165.47.65</ip>
    <port>5678</port>
    <type>socks4</type>
    <anonymity>elite</anonymity>
</45>
<46>
    <country>Poland</country>
    <ip>91.227.105.231</ip>
    <port>5678</port>
    <type>socks4</type>
    <anonymity>elite</anonymity>
</46>
<47>
    <country>Germany</country>
    <ip>51.77.73.68</ip>
    <port>31979</port>
    <type>socks4</type>
    <anonymity>elite</anonymity>
</47>
<48>
    <country>Korea, Republic of</country>
    <ip>125.141.133.47</ip>
    <port>5566</port>
    <type>socks4</type>
    <anonymity>elite</anonymity>
</48>
<49>
    <country>Thailand</country>
    <ip>171.97.107.187</ip>
    <port>4145</port>
    <type>socks4</type>
    <anonymity>elite</anonymity>
</49>
<50>
    <country>Thailand</country>
    <ip>43.249.68.245</ip>
    <port>1080</port>
    <type>socks4</type>
    <anonymity>elite</anonymity>
</50>
<51>
    <country>United States of America</country>
    <ip>104.16.106.234</ip>
    <port>80</port>
    <type>socks4</type>
    <anonymity>elite</anonymity>
</51>
<52>
    <country>Viet Nam</country>
    <ip>103.121.89.159</ip>
    <port>39267</port>
    <type>socks4</type>
    <anonymity>elite</anonymity>
</52>
<53>
    <country>Thailand</country>
    <ip>110.78.149.110</ip>
    <port>4145</port>
    <type>socks4</type>
    <anonymity>elite</anonymity>
</53>
<54>
    <country>Germany</country>
    <ip>5.9.169.87</ip>
    <port>30000</port>
    <type>socks4</type>
    <anonymity>elite</anonymity>
</54>
<55>
    <country>United States of America</country>
    <ip>104.35.140.42</ip>
    <port>80</port>
    <type>socks4</type>
    <anonymity>elite</anonymity>
</55>
<56>
    <country>Brazil</country>
    <ip>187.67.87.42</ip>
    <port>4145</port>
    <type>socks4</type>
    <anonymity>elite</anonymity>
</56>
<57>
    <country>Ecuador</country>
    <ip>186.4.247.48</ip>
    <port>51327</port>
    <type>socks4</type>
    <anonymity>elite</anonymity>
</57>
<58>
    <country>Indonesia</country>
    <ip>36.93.190.39</ip>
    <port>1080</port>
    <type>socks4</type>
    <anonymity>elite</anonymity>
</58>
<59>
    <country>Brazil</country>
    <ip>201.76.122.177</ip>
    <port>20183</port>
    <type>socks4</type>
    <anonymity>elite</anonymity>
</59>
<60>
    <country>Canada</country>
    <ip>54.39.46.86</ip>
    <port>3128</port>
    <type>socks4</type>
    <anonymity>elite</anonymity>
</60>
<61>
    <country>Indonesia</country>
    <ip>103.79.96.217</ip>
    <port>4153</port>
    <type>socks4</type>
    <anonymity>elite</anonymity>
</61>
<62>
    <country>Seychelles</country>
    <ip>197.234.13.63</ip>
    <port>4145</port>
    <type>socks4</type>
    <anonymity>elite</anonymity>
</62>
<63>
    <country>Kazakhstan</country>
    <ip>212.154.251.210</ip>
    <port>5678</port>
    <type>socks4</type>
    <anonymity>elite</anonymity>
</63>
<64>
    <country>United States of America</country>
    <ip>208.109.39.171</ip>
    <port>58438</port>
    <type>socks4</type>
    <anonymity>elite</anonymity>
</64>
<65>
    <country>United States of America</country>
    <ip>104.16.213.202</ip>
    <port>80</port>
    <type>socks4</type>
    <anonymity>elite</anonymity>
</65>
<66>
    <country>Brazil</country>
    <ip>170.244.64.198</ip>
    <port>31476</port>
    <type>socks4</type>
    <anonymity>elite</anonymity>
</66>
<67>
    <country>United States of America</country>
    <ip>18.216.228.146</ip>
    <port>38209</port>
    <type>socks4</type>
    <anonymity>elite</anonymity>
</67>
<68>
    <country>United States of America</country>
    <ip>172.96.172.149</ip>
    <port>59400</port>
    <type>socks4</type>
    <anonymity>elite</anonymity>
</68>
<69>
    <country>United States of America</country>
    <ip>178.254.168.12</ip>
    <port>4782</port>
    <type>socks4</type>
    <anonymity>elite</anonymity>
</69>
<70>
    <country>Germany</country>
    <ip>45.8.107.79</ip>
    <port>80</port>
    <type>socks4</type>
    <anonymity>elite</anonymity>
</70>
<71>
    <country>United States of America</country>
    <ip>104.19.124.112</ip>
    <port>80</port>
    <type>socks4</type>
    <anonymity>elite</anonymity>
</71>
<72>
    <country>Thailand</country>
    <ip>110.77.184.98</ip>
    <port>4145</port>
    <type>socks4</type>
    <anonymity>elite</anonymity>
</72>
<73>
    <country>United States of America</country>
    <ip>23.94.73.177</ip>
    <port>22429</port>
    <type>socks4</type>
    <anonymity>elite</anonymity>
</73>
<74>
    <country>Indonesia</country>
    <ip>36.37.104.99</ip>
    <port>34040</port>
    <type>socks4</type>
    <anonymity>elite</anonymity>
</74>
<75>
    <country>India</country>
    <ip>103.103.143.63</ip>
    <port>5678</port>
    <type>socks4</type>
    <anonymity>elite</anonymity>
</75>
<76>
    <country>China</country>
    <ip>106.3.142.85</ip>
    <port>4153</port>
    <type>socks4</type>
    <anonymity>elite</anonymity>
</76>
<77>
    <country>Brazil</country>
    <ip>168.197.28.220</ip>
    <port>4145</port>
    <type>socks4</type>
    <anonymity>elite</anonymity>
</77>
<78>
    <country>Hong Kong</country>
    <ip>47.52.240.190</ip>
    <port>808</port>
    <type>socks4</type>
    <anonymity>elite</anonymity>
</78>
<79>
    <country>China</country>
    <ip>140.237.144.43</ip>
    <port>53309</port>
    <type>socks4</type>
    <anonymity>elite</anonymity>
</79>
<80>
    <country>Brazil</country>
    <ip>201.20.88.5</ip>
    <port>3128</port>
    <type>socks4</type>
    <anonymity>elite</anonymity>
</80>
<81>
    <country>United States of America</country>
    <ip>66.228.38.127</ip>
    <port>11797</port>
    <type>socks4</type>
    <anonymity>elite</anonymity>
</81>
<82>
    <country>Viet Nam</country>
    <ip>115.75.5.17</ip>
    <port>38351</port>
    <type>socks4</type>
    <anonymity>elite</anonymity>
</82>
<83>
    <country>Korea, Republic of</country>
    <ip>211.174.105.18</ip>
    <port>4153</port>
    <type>socks4</type>
    <anonymity>elite</anonymity>
</83>
<84>
    <country>Thailand</country>
    <ip>119.42.86.104</ip>
    <port>4145</port>
    <type>socks4</type>
    <anonymity>elite</anonymity>
</84>
<85>
    <country>Russian Federation</country>
    <ip>188.43.20.173</ip>
    <port>4153</port>
    <type>socks4</type>
    <anonymity>elite</anonymity>
</85>
<86>
    <country>Poland</country>
    <ip>185.32.4.98</ip>
    <port>4153</port>
    <type>socks4</type>
    <anonymity>elite</anonymity>
</86>
<87>
    <country>Thailand</country>
    <ip>159.192.97.156</ip>
    <port>4145</port>
    <type>socks4</type>
    <anonymity>elite</anonymity>
</87>
<88>
    <country>Sweden</country>
    <ip>185.6.8.108</ip>
    <port>19427</port>
    <type>socks4</type>
    <anonymity>elite</anonymity>
</88>
<89>
    <country>India</country>
    <ip>116.199.172.1</ip>
    <port>4145</port>
    <type>socks4</type>
    <anonymity>elite</anonymity>
</89>
<90>
    <country>Iran, Islamic Republic of</country>
    <ip>81.12.124.113</ip>
    <port>5678</port>
    <type>socks4</type>
    <anonymity>elite</anonymity>
</90>
<91>
    <country>Poland</country>
    <ip>31.11.172.54</ip>
    <port>4153</port>
    <type>socks4</type>
    <anonymity>elite</anonymity>
</91>
<92>
    <country>Brazil</country>
    <ip>187.85.157.30</ip>
    <port>5678</port>
    <type>socks4</type>
    <anonymity>elite</anonymity>
</92>
<93>
    <country>Brazil</country>
    <ip>170.254.255.253</ip>
    <port>45816</port>
    <type>socks4</type>
    <anonymity>elite</anonymity>
</93>
<94>
    <country>Türkiye</country>
    <ip>78.186.111.34</ip>
    <port>1080</port>
    <type>socks4</type>
    <anonymity>elite</anonymity>
</94>
<95>
    <country>Singapore</country>
    <ip>43.134.237.27</ip>
    <port>443</port>
    <type>socks4</type>
    <anonymity>elite</anonymity>
</95>
<96>
    <country>Brazil</country>
    <ip>179.96.142.75</ip>
    <port>5678</port>
    <type>socks4</type>
    <anonymity>elite</anonymity>
</96>
<97>
    <country>Bangladesh</country>
    <ip>43.240.103.178</ip>
    <port>1088</port>
    <type>socks4</type>
    <anonymity>elite</anonymity>
</97>
<98>
    <country>United States of America</country>
    <ip>172.67.254.127</ip>
    <port>80</port>
    <type>socks4</type>
    <anonymity>elite</anonymity>
</98>
<99>
    <country>Japan</country>
    <ip>43.153.173.244</ip>
    <port>443</port>
    <type>socks4</type>
    <anonymity>elite</anonymity>
</99>
<100>
    <country>Germany</country>
    <ip>144.76.14.199</ip>
    <port>14705</port>
    <type>socks4</type>
    <anonymity>elite</anonymity>
</100>
<101>
    <country>Hong Kong</country>
    <ip>165.84.180.124</ip>
    <port>45927</port>
    <type>socks4</type>
    <anonymity>elite</anonymity>
</101>
<102>
    <country>United States of America</country>
    <ip>38.127.179.124</ip>
    <port>15290</port>
    <type>socks4</type>
    <anonymity>elite</anonymity>
</102>
<103>
    <country>Germany</country>
    <ip>5.9.141.52</ip>
    <port>30000</port>
    <type>socks4</type>
    <anonymity>elite</anonymity>
</103>
<104>
    <country>Brazil</country>
    <ip>45.7.177.244</ip>
    <port>39867</port>
    <type>socks4</type>
    <anonymity>elite</anonymity>
</104>
<105>
    <country>India</country>
    <ip>103.39.236.205</ip>
    <port>8080</port>
    <type>socks4</type>
    <anonymity>elite</anonymity>
</105>
<106>
    <country>United States of America</country>
    <ip>198.251.79.65</ip>
    <port>3128</port>
    <type>socks4</type>
    <anonymity>elite</anonymity>
</106>
<107>
    <country>United States of America</country>
    <ip>67.43.42.117</ip>
    <port>8080</port>
    <type>socks4</type>
    <anonymity>elite</anonymity>
</107>
<108>
    <country>China</country>
    <ip>183.217.204.97</ip>
    <port>8123</port>
    <type>socks4</type>
    <anonymity>elite</anonymity>
</108>
<109>
    <country>Brazil</country>
    <ip>170.254.255.239</ip>
    <port>45816</port>
    <type>socks4</type>
    <anonymity>elite</anonymity>
</109>
<110>
    <country>United States of America</country>
    <ip>154.29.227.162</ip>
    <port>8081</port>
    <type>socks4</type>
    <anonymity>elite</anonymity>
</110>
<111>
    <country>Seychelles</country>
    <ip>197.234.13.45</ip>
    <port>4145</port>
    <type>socks4</type>
    <anonymity>elite</anonymity>
</111>
<112>
    <country>Thailand</country>
    <ip>1.10.133.132</ip>
    <port>4145</port>
    <type>socks4</type>
    <anonymity>elite</anonymity>
</112>
<113>
    <country>Ukraine</country>
    <ip>91.90.16.211</ip>
    <port>1080</port>
    <type>socks4</type>
    <anonymity>elite</anonymity>
</113>
<114>
    <country>China</country>
    <ip>114.104.141.138</ip>
    <port>38801</port>
    <type>socks4</type>
    <anonymity>elite</anonymity>
</114>
<115>
    <country>Brazil</country>
    <ip>177.184.67.73</ip>
    <port>4145</port>
    <type>socks4</type>
    <anonymity>elite</anonymity>
</115>
<116>
    <country>Ukraine</country>
    <ip>85.159.4.125</ip>
    <port>5678</port>
    <type>socks4</type>
    <anonymity>elite</anonymity>
</116>
<117>
    <country>Viet Nam</country>
    <ip>171.244.68.28</ip>
    <port>5678</port>
    <type>socks4</type>
    <anonymity>elite</anonymity>
</117>
<118>
    <country>United States of America</country>
    <ip>104.19.5.247</ip>
    <port>80</port>
    <type>socks4</type>
    <anonymity>elite</anonymity>
</118>
<119>
    <country>Thailand</country>
    <ip>183.89.41.115</ip>
    <port>5678</port>
    <type>socks4</type>
    <anonymity>elite</anonymity>
</119>
<120>
    <country>Palestine, State of</country>
    <ip>5.133.30.126</ip>
    <port>5678</port>
    <type>socks4</type>
    <anonymity>elite</anonymity>
</120>
<121>
    <country>China</country>
    <ip>218.106.167.98</ip>
    <port>4145</port>
    <type>socks4</type>
    <anonymity>elite</anonymity>
</121>
<122>
    <country>Iran, Islamic Republic of</country>
    <ip>185.125.253.218</ip>
    <port>1080</port>
    <type>socks4</type>
    <anonymity>elite</anonymity>
</122>
<123>
    <country>Argentina</country>
    <ip>181.101.1.221</ip>
    <port>7071</port>
    <type>socks4</type>
    <anonymity>elite</anonymity>
</123>
<124>
    <country>Brazil</country>
    <ip>177.184.67.81</ip>
    <port>4145</port>
    <type>socks4</type>
    <anonymity>elite</anonymity>
</124>
<125>
    <country>Serbia</country>
    <ip>178.253.208.146</ip>
    <port>1080</port>
    <type>socks4</type>
    <anonymity>elite</anonymity>
</125>
<126>
    <country>Spain</country>
    <ip>83.53.207.196</ip>
    <port>4145</port>
    <type>socks4</type>
    <anonymity>elite</anonymity>
</126>
<127>
    <country>United Kingdom of Great Britain and Northern Ireland</country>
    <ip>154.16.63.16</ip>
    <port>443</port>
    <type>socks4</type>
    <anonymity>elite</anonymity>
</127>
<128>
    <country>Chile</country>
    <ip>190.121.21.211</ip>
    <port>51963</port>
    <type>socks4</type>
    <anonymity>elite</anonymity>
</128>
<129>
    <country>Russian Federation</country>
    <ip>80.73.87.202</ip>
    <port>4153</port>
    <type>socks4</type>
    <anonymity>elite</anonymity>
</129>
<130>
    <country>Poland</country>
    <ip>155.133.83.169</ip>
    <port>58351</port>
    <type>socks4</type>
    <anonymity>elite</anonymity>
</130>
<131>
    <country>Russian Federation</country>
    <ip>178.184.12.244</ip>
    <port>8081</port>
    <type>socks4</type>
    <anonymity>elite</anonymity>
</131>
<132>
    <country>Thailand</country>
    <ip>1.20.207.225</ip>
    <port>4153</port>
    <type>socks4</type>
    <anonymity>elite</anonymity>
</132>
<133>
    <country>Ireland</country>
    <ip>185.104.219.229</ip>
    <port>80</port>
    <type>socks4</type>
    <anonymity>elite</anonymity>
</133>
<134>
    <country>Thailand</country>
    <ip>183.89.40.190</ip>
    <port>1080</port>
    <type>socks4</type>
    <anonymity>elite</anonymity>
</134>
<135>
    <country>Russian Federation</country>
    <ip>46.23.155.18</ip>
    <port>62638</port>
    <type>socks4</type>
    <anonymity>elite</anonymity>
</135>
<136>
    <country>China</country>
    <ip>123.59.100.245</ip>
    <port>1080</port>
    <type>socks4</type>
    <anonymity>elite</anonymity>
</136>
<137>
    <country>South Africa</country>
    <ip>102.66.237.13</ip>
    <port>5678</port>
    <type>socks4</type>
    <anonymity>elite</anonymity>
</137>
<138>
    <country>Poland</country>
    <ip>155.133.83.253</ip>
    <port>58351</port>
    <type>socks4</type>
    <anonymity>elite</anonymity>
</138>
<139>
    <country>Brazil</country>
    <ip>45.7.177.201</ip>
    <port>39867</port>
    <type>socks4</type>
    <anonymity>elite</anonymity>
</139>
<140>
    <country>China</country>
    <ip>58.35.208.107</ip>
    <port>5678</port>
    <type>socks4</type>
    <anonymity>elite</anonymity>
</140>
<141>
    <country>Indonesia</country>
    <ip>103.242.104.246</ip>
    <port>5678</port>
    <type>socks4</type>
    <anonymity>elite</anonymity>
</141>
<142>
    <country>Russian Federation</country>
    <ip>94.79.54.7</ip>
    <port>51439</port>
    <type>socks4</type>
    <anonymity>elite</anonymity>
</142>
<143>
    <country>Brazil</country>
    <ip>45.7.177.196</ip>
    <port>39867</port>
    <type>socks4</type>
    <anonymity>elite</anonymity>
</143>
<144>
    <country>Thailand</country>
    <ip>180.183.135.241</ip>
    <port>1099</port>
    <type>socks4</type>
    <anonymity>elite</anonymity>
</144>
<145>
    <country>Bangladesh</country>
    <ip>103.229.85.22</ip>
    <port>4145</port>
    <type>socks4</type>
    <anonymity>elite</anonymity>
</145>
<146>
    <country>Brazil</country>
    <ip>168.227.158.85</ip>
    <port>4145</port>
    <type>socks4</type>
    <anonymity>elite</anonymity>
</146>
<147>
    <country>Thailand</country>
    <ip>180.183.215.154</ip>
    <port>4153</port>
    <type>socks4</type>
    <anonymity>elite</anonymity>
</147>
<148>
    <country>India</country>
    <ip>139.59.90.141</ip>
    <port>80</port>
    <type>socks4</type>
    <anonymity>elite</anonymity>
</148>
<149>
    <country>Indonesia</country>
    <ip>103.110.184.1</ip>
    <port>6037</port>
    <type>socks4</type>
    <anonymity>elite</anonymity>
</149>
<150>
    <country>Costa Rica</country>
    <ip>170.80.91.13</ip>
    <port>4145</port>
    <type>socks4</type>
    <anonymity>elite</anonymity>
</150>
<151>
    <country>Indonesia</country>
    <ip>103.137.8.98</ip>
    <port>4153</port>
    <type>socks4</type>
    <anonymity>elite</anonymity>
</151>
<152>
    <country>India</country>
    <ip>103.70.159.130</ip>
    <port>5678</port>
    <type>socks4</type>
    <anonymity>elite</anonymity>
</152>
<153>
    <country>Indonesia</country>
    <ip>45.112.125.53</ip>
    <port>4145</port>
    <type>socks4</type>
    <anonymity>elite</anonymity>
</153>
<154>
    <country>Chile</country>
    <ip>190.114.253.210</ip>
    <port>3389</port>
    <type>socks4</type>
    <anonymity>elite</anonymity>
</154>
<155>
    <country>Thailand</country>
    <ip>124.122.137.150</ip>
    <port>4153</port>
    <type>socks4</type>
    <anonymity>elite</anonymity>
</155>
<156>
    <country>Iran, Islamic Republic of</country>
    <ip>185.171.55.218</ip>
    <port>4153</port>
    <type>socks4</type>
    <anonymity>elite</anonymity>
</156>
<157>
    <country>Iran, Islamic Republic of</country>
    <ip>185.171.54.36</ip>
    <port>4153</port>
    <type>socks4</type>
    <anonymity>elite</anonymity>
</157>
<158>
    <country>China</country>
    <ip>202.136.215.29</ip>
    <port>808</port>
    <type>socks4</type>
    <anonymity>elite</anonymity>
</158>
<159>
    <country>Brazil</country>
    <ip>45.7.177.214</ip>
    <port>39867</port>
    <type>socks4</type>
    <anonymity>elite</anonymity>
</159>
<160>
    <country>Japan</country>
    <ip>43.153.177.147</ip>
    <port>443</port>
    <type>socks4</type>
    <anonymity>elite</anonymity>
</160>
<161>
    <country>China</country>
    <ip>140.250.150.56</ip>
    <port>1080</port>
    <type>socks4</type>
    <anonymity>elite</anonymity>
</161>
<162>
    <country>United States of America</country>
    <ip>209.143.1.244</ip>
    <port>80</port>
    <type>socks4</type>
    <anonymity>elite</anonymity>
</162>
<163>
    <country>Bangladesh</country>
    <ip>103.121.62.14</ip>
    <port>5678</port>
    <type>socks4</type>
    <anonymity>elite</anonymity>
</163>
<164>
    <country>China</country>
    <ip>49.233.61.206</ip>
    <port>2080</port>
    <type>socks4</type>
    <anonymity>elite</anonymity>
</164>
<165>
    <country>Poland</country>
    <ip>85.222.67.66</ip>
    <port>5678</port>
    <type>socks4</type>
    <anonymity>elite</anonymity>
</165>
<166>
    <country>Indonesia</country>
    <ip>202.159.35.65</ip>
    <port>443</port>
    <type>socks4</type>
    <anonymity>elite</anonymity>
</166>
<167>
    <country>Singapore</country>
    <ip>43.134.169.115</ip>
    <port>443</port>
    <type>socks4</type>
    <anonymity>elite</anonymity>
</167>
<168>
    <country>Bangladesh</country>
    <ip>103.229.85.209</ip>
    <port>4145</port>
    <type>socks4</type>
    <anonymity>elite</anonymity>
</168>
<169>
    <country>Seychelles</country>
    <ip>197.234.13.10</ip>
    <port>4145</port>
    <type>socks4</type>
    <anonymity>elite</anonymity>
</169>
<170>
    <country>Colombia</country>
    <ip>181.78.13.91</ip>
    <port>5678</port>
    <type>socks4</type>
    <anonymity>elite</anonymity>
</170>
<171>
    <country>Bangladesh</country>
    <ip>103.35.108.198</ip>
    <port>4145</port>
    <type>socks4</type>
    <anonymity>elite</anonymity>
</171>
<172>
    <country>Brazil</country>
    <ip>45.7.176.78</ip>
    <port>52246</port>
    <type>socks4</type>
    <anonymity>elite</anonymity>
</172>
<173>
    <country>Colombia</country>
    <ip>200.116.198.177</ip>
    <port>32072</port>
    <type>socks4</type>
    <anonymity>elite</anonymity>
</173>
<174>
    <country>Türkiye</country>
    <ip>85.100.40.12</ip>
    <port>5678</port>
    <type>socks4</type>
    <anonymity>elite</anonymity>
</174>
<175>
    <country>Brazil</country>
    <ip>186.208.19.61</ip>
    <port>5678</port>
    <type>socks4</type>
    <anonymity>elite</anonymity>
</175>
<176>
    <country>Czechia</country>
    <ip>193.8.87.85</ip>
    <port>4444</port>
    <type>socks4</type>
    <anonymity>elite</anonymity>
</176>
<177>
    <country>Ukraine</country>
    <ip>93.171.224.59</ip>
    <port>4153</port>
    <type>socks4</type>
    <anonymity>elite</anonymity>
</177>
<178>
    <country>Thailand</country>
    <ip>180.180.152.94</ip>
    <port>4145</port>
    <type>socks4</type>
    <anonymity>elite</anonymity>
</178>
<179>
    <country>United States of America</country>
    <ip>70.185.95.162</ip>
    <port>39593</port>
    <type>socks4</type>
    <anonymity>elite</anonymity>
</179>
<180>
    <country>Indonesia</country>
    <ip>116.197.135.85</ip>
    <port>1080</port>
    <type>socks4</type>
    <anonymity>elite</anonymity>
</180>
<181>
    <country>Bulgaria</country>
    <ip>213.149.156.87</ip>
    <port>5678</port>
    <type>socks4</type>
    <anonymity>elite</anonymity>
</181>
<182>
    <country>Indonesia</country>
    <ip>36.67.147.221</ip>
    <port>4153</port>
    <type>socks4</type>
    <anonymity>elite</anonymity>
</182>
<183>
    <country>Poland</country>
    <ip>77.65.23.74</ip>
    <port>5678</port>
    <type>socks4</type>
    <anonymity>elite</anonymity>
</183>
<184>
    <country>Indonesia</country>
    <ip>182.253.159.166</ip>
    <port>5678</port>
    <type>socks4</type>
    <anonymity>elite</anonymity>
</184>
<185>
    <country>Ukraine</country>
    <ip>195.78.100.186</ip>
    <port>3629</port>
    <type>socks4</type>
    <anonymity>elite</anonymity>
</185>
<186>
    <country>United States of America</country>
    <ip>104.17.9.114</ip>
    <port>80</port>
    <type>socks4</type>
    <anonymity>elite</anonymity>
</186>
<187>
    <country>Singapore</country>
    <ip>129.126.65.78</ip>
    <port>4153</port>
    <type>socks4</type>
    <anonymity>elite</anonymity>
</187>
<188>
    <country>Bulgaria</country>
    <ip>89.25.23.210</ip>
    <port>4153</port>
    <type>socks4</type>
    <anonymity>elite</anonymity>
</188>
<189>
    <country>Türkiye</country>
    <ip>185.169.181.13</ip>
    <port>4145</port>
    <type>socks4</type>
    <anonymity>elite</anonymity>
</189>
<190>
    <country>Cambodia</country>
    <ip>202.124.46.102</ip>
    <port>4145</port>
    <type>socks4</type>
    <anonymity>elite</anonymity>
</190>
<191>
    <country>Ukraine</country>
    <ip>195.138.65.34</ip>
    <port>5678</port>
    <type>socks4</type>
    <anonymity>elite</anonymity>
</191>
<192>
    <country>Russian Federation</country>
    <ip>89.237.34.13</ip>
    <port>51549</port>
    <type>socks4</type>
    <anonymity>elite</anonymity>
</192>
<193>
    <country>India</country>
    <ip>103.199.97.9</ip>
    <port>39825</port>
    <type>socks4</type>
    <anonymity>elite</anonymity>
</193>
<194>
    <country>Brazil</country>
    <ip>177.38.5.42</ip>
    <port>4153</port>
    <type>socks4</type>
    <anonymity>elite</anonymity>
</194>
<195>
    <country>India</country>
    <ip>103.251.221.49</ip>
    <port>4145</port>
    <type>socks4</type>
    <anonymity>elite</anonymity>
</195>
<196>
    <country>United States of America</country>
    <ip>37.1.211.58</ip>
    <port>1080</port>
    <type>socks4</type>
    <anonymity>elite</anonymity>
</196>
<197>
    <country>Viet Nam</country>
    <ip>115.73.220.114</ip>
    <port>5678</port>
    <type>socks4</type>
    <anonymity>elite</anonymity>
</197>
<198>
    <country>Brazil</country>
    <ip>45.7.177.233</ip>
    <port>39867</port>
    <type>socks4</type>
    <anonymity>elite</anonymity>
</198>
<199>
    <country>China</country>
    <ip>58.246.245.122</ip>
    <port>4153</port>
    <type>socks4</type>
    <anonymity>elite</anonymity>
</199>
<200>
    <country>Thailand</country>
    <ip>183.89.176.143</ip>
    <port>5678</port>
    <type>socks4</type>
    <anonymity>elite</anonymity>
</200>
<201>
    <country>United States of America</country>
    <ip>143.198.229.225</ip>
    <port>3240</port>
    <type>socks4</type>
    <anonymity>elite</anonymity>
</201>
<202>
    <country>Brazil</country>
    <ip>45.7.177.245</ip>
    <port>39867</port>
    <type>socks4</type>
    <anonymity>elite</anonymity>
</202>
<203>
    <country>Germany</country>
    <ip>45.14.174.180</ip>
    <port>80</port>
    <type>socks4</type>
    <anonymity>elite</anonymity>
</203>
<204>
    <country>Germany</country>
    <ip>148.251.232.232</ip>
    <port>30064</port>
    <type>socks4</type>
    <anonymity>elite</anonymity>
</204>
<205>
    <country>Moldova, Republic of</country>
    <ip>185.46.60.108</ip>
    <port>5678</port>
    <type>socks4</type>
    <anonymity>elite</anonymity>
</205>
<206>
    <country>Brazil</country>
    <ip>177.126.89.76</ip>
    <port>8080</port>
    <type>socks4</type>
    <anonymity>elite</anonymity>
</206>
<207>
    <country>United States of America</country>
    <ip>162.255.108.254</ip>
    <port>5678</port>
    <type>socks4</type>
    <anonymity>elite</anonymity>
</207>
<208>
    <country>Lesotho</country>
    <ip>154.66.108.52</ip>
    <port>3629</port>
    <type>socks4</type>
    <anonymity>elite</anonymity>
</208>
<209>
    <country>Singapore</country>
    <ip>178.128.49.205</ip>
    <port>80</port>
    <type>socks4</type>
    <anonymity>elite</anonymity>
</209>
<210>
    <country>India</country>
    <ip>103.66.233.177</ip>
    <port>4145</port>
    <type>socks4</type>
    <anonymity>elite</anonymity>
</210>
<211>
    <country>India</country>
    <ip>103.53.110.45</ip>
    <port>10801</port>
    <type>socks4</type>
    <anonymity>elite</anonymity>
</211>
<212>
    <country>China</country>
    <ip>106.75.152.204</ip>
    <port>999</port>
    <type>socks4</type>
    <anonymity>elite</anonymity>
</212>
<213>
    <country>India</country>
    <ip>103.70.159.144</ip>
    <port>5678</port>
    <type>socks4</type>
    <anonymity>elite</anonymity>
</213>
<214>
    <country>China</country>
    <ip>140.250.93.245</ip>
    <port>1080</port>
    <type>socks4</type>
    <anonymity>elite</anonymity>
</214>
<215>
    <country>Brazil</country>
    <ip>45.7.177.250</ip>
    <port>39867</port>
    <type>socks4</type>
    <anonymity>elite</anonymity>
</215>
<216>
    <country>United States of America</country>
    <ip>43.153.3.241</ip>
    <port>443</port>
    <type>socks4</type>
    <anonymity>elite</anonymity>
</216>
<217>
    <country>Moldova, Republic of</country>
    <ip>37.221.67.62</ip>
    <port>5555</port>
    <type>socks4</type>
    <anonymity>elite</anonymity>
</217>
<218>
    <country>India</country>
    <ip>45.127.222.94</ip>
    <port>5678</port>
    <type>socks4</type>
    <anonymity>elite</anonymity>
</218>
<219>
    <country>Mexico</country>
    <ip>189.219.53.209</ip>
    <port>10000</port>
    <type>socks4</type>
    <anonymity>elite</anonymity>
</219>
<220>
    <country>India</country>
    <ip>103.24.21.1</ip>
    <port>5678</port>
    <type>socks4</type>
    <anonymity>elite</anonymity>
</220>
<221>
    <country>Indonesia</country>
    <ip>202.72.209.3</ip>
    <port>44550</port>
    <type>socks4</type>
    <anonymity>elite</anonymity>
</221>
<222>
    <country>India</country>
    <ip>43.246.143.250</ip>
    <port>9999</port>
    <type>socks4</type>
    <anonymity>elite</anonymity>
</222>
<223>
    <country>Russian Federation</country>
    <ip>92.38.45.72</ip>
    <port>3629</port>
    <type>socks4</type>
    <anonymity>elite</anonymity>
</223>
<224>
    <country>Indonesia</country>
    <ip>117.102.78.163</ip>
    <port>1080</port>
    <type>socks4</type>
    <anonymity>elite</anonymity>
</224>
<225>
    <country>Bangladesh</country>
    <ip>118.67.216.94</ip>
    <port>4145</port>
    <type>socks4</type>
    <anonymity>elite</anonymity>
</225>
<226>
    <country>Thailand</country>
    <ip>183.89.116.141</ip>
    <port>4145</port>
    <type>socks4</type>
    <anonymity>elite</anonymity>
</226>
<227>
    <country>Viet Nam</country>
    <ip>113.160.203.118</ip>
    <port>5678</port>
    <type>socks4</type>
    <anonymity>elite</anonymity>
</227>
<228>
    <country>India</country>
    <ip>103.70.159.129</ip>
    <port>5678</port>
    <type>socks4</type>
    <anonymity>elite</anonymity>
</228>
<229>
    <country>Luxembourg</country>
    <ip>213.135.234.101</ip>
    <port>4153</port>
    <type>socks4</type>
    <anonymity>elite</anonymity>
</229>
<230>
    <country>Brazil</country>
    <ip>45.7.177.189</ip>
    <port>39867</port>
    <type>socks4</type>
    <anonymity>elite</anonymity>
</230>
<231>
    <country>India</country>
    <ip>163.53.83.124</ip>
    <port>5678</port>
    <type>socks4</type>
    <anonymity>elite</anonymity>
</231>
<232>
    <country>Viet Nam</country>
    <ip>27.72.145.184</ip>
    <port>5678</port>
    <type>socks4</type>
    <anonymity>elite</anonymity>
</232>
<233>
    <country>United States of America</country>
    <ip>104.17.166.210</ip>
    <port>80</port>
    <type>socks4</type>
    <anonymity>elite</anonymity>
</233>
<234>
    <country>Brazil</country>
    <ip>187.95.82.146</ip>
    <port>3629</port>
    <type>socks4</type>
    <anonymity>elite</anonymity>
</234>
<235>
    <country>United States of America</country>
    <ip>50.201.133.122</ip>
    <port>3355</port>
    <type>socks4</type>
    <anonymity>elite</anonymity>
</235>
<236>
    <country>Argentina</country>
    <ip>200.41.148.2</ip>
    <port>12000</port>
    <type>socks4</type>
    <anonymity>elite</anonymity>
</236>
<237>
    <country>United States of America</country>
    <ip>104.17.37.235</ip>
    <port>80</port>
    <type>socks4</type>
    <anonymity>elite</anonymity>
</237>
<238>
    <country>Netherlands</country>
    <ip>193.242.210.140</ip>
    <port>80</port>
    <type>socks4</type>
    <anonymity>elite</anonymity>
</238>
<239>
    <country>India</country>
    <ip>103.59.203.189</ip>
    <port>4145</port>
    <type>socks4</type>
    <anonymity>elite</anonymity>
</239>
<240>
    <country>India</country>
    <ip>103.47.93.254</ip>
    <port>1080</port>
    <type>socks4</type>
    <anonymity>elite</anonymity>
</240>
<241>
    <country>Ecuador</country>
    <ip>181.198.32.211</ip>
    <port>4153</port>
    <type>socks4</type>
    <anonymity>elite</anonymity>
</241>
<242>
    <country>United States of America</country>
    <ip>75.119.202.168</ip>
    <port>32524</port>
    <type>socks4</type>
    <anonymity>elite</anonymity>
</242>
<243>
    <country>Colombia</country>
    <ip>190.0.22.34</ip>
    <port>61155</port>
    <type>socks4</type>
    <anonymity>elite</anonymity>
</243>
<244>
    <country>United States of America</country>
    <ip>51.81.31.66</ip>
    <port>54535</port>
    <type>socks4</type>
    <anonymity>elite</anonymity>
</244>
<245>
    <country>Ukraine</country>
    <ip>109.207.193.135</ip>
    <port>5678</port>
    <type>socks4</type>
    <anonymity>elite</anonymity>
</245>
<246>
    <country>Russian Federation</country>
    <ip>89.237.33.65</ip>
    <port>51549</port>
    <type>socks4</type>
    <anonymity>elite</anonymity>
</246>
<247>
    <country>Brazil</country>
    <ip>45.70.204.21</ip>
    <port>4145</port>
    <type>socks4</type>
    <anonymity>elite</anonymity>
</247>
<248>
    <country>India</country>
    <ip>144.48.178.62</ip>
    <port>83</port>
    <type>socks4</type>
    <anonymity>elite</anonymity>
</248>
<249>
    <country>Thailand</country>
    <ip>180.183.225.197</ip>
    <port>4145</port>
    <type>socks4</type>
    <anonymity>elite</anonymity>
</249>
<250>
    <country>Nepal</country>
    <ip>202.79.40.97</ip>
    <port>36953</port>
    <type>socks4</type>
    <anonymity>elite</anonymity>
</250>
<251>
    <country>Brazil</country>
    <ip>170.238.180.21</ip>
    <port>4145</port>
    <type>socks4</type>
    <anonymity>elite</anonymity>
</251>
<252>
    <country>Argentina</country>
    <ip>200.43.231.8</ip>
    <port>4153</port>
    <type>socks4</type>
    <anonymity>elite</anonymity>
</252>
<253>
    <country>United States of America</country>
    <ip>38.127.179.226</ip>
    <port>55994</port>
    <type>socks4</type>
    <anonymity>elite</anonymity>
</253>
<254>
    <country>Germany</country>
    <ip>43.157.53.134</ip>
    <port>443</port>
    <type>socks4</type>
    <anonymity>elite</anonymity>
</254>
<255>
    <country>France</country>
    <ip>162.12.217.70</ip>
    <port>3629</port>
    <type>socks4</type>
    <anonymity>elite</anonymity>
</255>
<256>
    <country>Thailand</country>
    <ip>49.49.74.204</ip>
    <port>5678</port>
    <type>socks4</type>
    <anonymity>elite</anonymity>
</256>
<257>
    <country>United States of America</country>
    <ip>66.33.209.193</ip>
    <port>10346</port>
    <type>socks4</type>
    <anonymity>elite</anonymity>
</257>
<258>
    <country>Argentina</country>
    <ip>200.0.247.85</ip>
    <port>4153</port>
    <type>socks4</type>
    <anonymity>elite</anonymity>
</258>
<259>
    <country>United States of America</country>
    <ip>67.205.191.44</ip>
    <port>8080</port>
    <type>socks4</type>
    <anonymity>elite</anonymity>
</259>
<260>
    <country>Cyprus</country>
    <ip>203.13.32.236</ip>
    <port>80</port>
    <type>socks4</type>
    <anonymity>elite</anonymity>
</260>
<261>
    <country>Lao People's Democratic Republic</country>
    <ip>202.137.141.183</ip>
    <port>5678</port>
    <type>socks4</type>
    <anonymity>elite</anonymity>
</261>
<262>
    <country>Finland</country>
    <ip>95.217.144.183</ip>
    <port>44965</port>
    <type>socks4</type>
    <anonymity>elite</anonymity>
</262>
<263>
    <country>China</country>
    <ip>111.225.153.169</ip>
    <port>8089</port>
    <type>socks4</type>
    <anonymity>elite</anonymity>
</263>
<264>
    <country>Poland</country>
    <ip>193.59.26.116</ip>
    <port>4153</port>
    <type>socks4</type>
    <anonymity>elite</anonymity>
</264>
<265>
    <country>India</country>
    <ip>117.241.135.33</ip>
    <port>5678</port>
    <type>socks4</type>
    <anonymity>elite</anonymity>
</265>
<266>
    <country>United States of America</country>
    <ip>50.192.49.195</ip>
    <port>32100</port>
    <type>socks4</type>
    <anonymity>elite</anonymity>
</266>
<267>
    <country>Nigeria</country>
    <ip>41.76.156.90</ip>
    <port>47313</port>
    <type>socks4</type>
    <anonymity>elite</anonymity>
</267>
<268>
    <country>United States of America</country>
    <ip>104.16.105.146</ip>
    <port>80</port>
    <type>socks4</type>
    <anonymity>elite</anonymity>
</268>
<269>
    <country>Brazil</country>
    <ip>177.125.160.69</ip>
    <port>4145</port>
    <type>socks4</type>
    <anonymity>elite</anonymity>
</269>
<270>
    <country>Netherlands</country>
    <ip>95.179.155.218</ip>
    <port>8080</port>
    <type>socks4</type>
    <anonymity>elite</anonymity>
</270>
<271>
    <country>India</country>
    <ip>59.98.148.27</ip>
    <port>5678</port>
    <type>socks4</type>
    <anonymity>elite</anonymity>
</271>
<272>
    <country>Japan</country>
    <ip>43.153.176.37</ip>
    <port>443</port>
    <type>socks4</type>
    <anonymity>elite</anonymity>
</272>
<273>
    <country>Indonesia</country>
    <ip>103.51.44.5</ip>
    <port>4145</port>
    <type>socks4</type>
    <anonymity>elite</anonymity>
</273>
<274>
    <country>Hong Kong</country>
    <ip>43.154.173.221</ip>
    <port>1080</port>
    <type>socks4</type>
    <anonymity>elite</anonymity>
</274>
<275>
    <country>Indonesia</country>
    <ip>202.159.35.201</ip>
    <port>443</port>
    <type>socks4</type>
    <anonymity>elite</anonymity>
</275>
<276>
    <country>Finland</country>
    <ip>135.181.79.170</ip>
    <port>22679</port>
    <type>socks4</type>
    <anonymity>elite</anonymity>
</276>
<277>
    <country>India</country>
    <ip>103.85.103.129</ip>
    <port>5678</port>
    <type>socks4</type>
    <anonymity>elite</anonymity>
</277>
<278>
    <country>Thailand</country>
    <ip>202.29.218.138</ip>
    <port>4153</port>
    <type>socks4</type>
    <anonymity>elite</anonymity>
</278>
<279>
    <country>Italy</country>
    <ip>185.238.159.9</ip>
    <port>32456</port>
    <type>socks4</type>
    <anonymity>elite</anonymity>
</279>
<280>
    <country>Russian Federation</country>
    <ip>188.133.155.215</ip>
    <port>1256</port>
    <type>socks4</type>
    <anonymity>elite</anonymity>
</280>
<281>
    <country>Serbia</country>
    <ip>79.101.106.74</ip>
    <port>33608</port>
    <type>socks4</type>
    <anonymity>elite</anonymity>
</281>
<282>
    <country>Zimbabwe</country>
    <ip>197.211.238.20</ip>
    <port>5678</port>
    <type>socks4</type>
    <anonymity>elite</anonymity>
</282>
<283>
    <country>India</country>
    <ip>103.66.233.161</ip>
    <port>4145</port>
    <type>socks4</type>
    <anonymity>elite</anonymity>
</283>
<284>
    <country>Thailand</country>
    <ip>110.78.146.161</ip>
    <port>4145</port>
    <type>socks4</type>
    <anonymity>elite</anonymity>
</284>
<285>
    <country>Azerbaijan</country>
    <ip>185.32.44.161</ip>
    <port>4153</port>
    <type>socks4</type>
    <anonymity>elite</anonymity>
</285>
<286>
    <country>United States of America</country>
    <ip>64.124.145.1</ip>
    <port>1080</port>
    <type>socks4</type>
    <anonymity>elite</anonymity>
</286>
<287>
    <country>China</country>
    <ip>120.136.21.230</ip>
    <port>10116</port>
    <type>socks4</type>
    <anonymity>elite</anonymity>
</287>
<288>
    <country>Bangladesh</country>
    <ip>103.109.56.209</ip>
    <port>1080</port>
    <type>socks4</type>
    <anonymity>elite</anonymity>
</288>
<289>
    <country>Thailand</country>
    <ip>110.78.141.219</ip>
    <port>4145</port>
    <type>socks4</type>
    <anonymity>elite</anonymity>
</289>
<290>
    <country>Ecuador</country>
    <ip>190.152.151.110</ip>
    <port>4673</port>
    <type>socks4</type>
    <anonymity>elite</anonymity>
</290>
<291>
    <country>Thailand</country>
    <ip>110.78.152.246</ip>
    <port>5678</port>
    <type>socks4</type>
    <anonymity>elite</anonymity>
</291>
<292>
    <country>Singapore</country>
    <ip>110.34.166.184</ip>
    <port>4153</port>
    <type>socks4</type>
    <anonymity>elite</anonymity>
</292>
<293>
    <country>United States of America</country>
    <ip>71.227.88.166</ip>
    <port>16913</port>
    <type>socks4</type>
    <anonymity>elite</anonymity>
</293>
<294>
    <country>Germany</country>
    <ip>148.251.84.230</ip>
    <port>60001</port>
    <type>socks4</type>
    <anonymity>elite</anonymity>
</294>
<295>
    <country>Brazil</country>
    <ip>189.109.224.170</ip>
    <port>8081</port>
    <type>socks4</type>
    <anonymity>elite</anonymity>
</295>
<296>
    <country>Thailand</country>
    <ip>182.52.32.11</ip>
    <port>4153</port>
    <type>socks4</type>
    <anonymity>elite</anonymity>
</296>
<297>
    <country>Brazil</country>
    <ip>186.211.6.137</ip>
    <port>4145</port>
    <type>socks4</type>
    <anonymity>elite</anonymity>
</297>
<298>
    <country>China</country>
    <ip>58.21.70.44</ip>
    <port>44844</port>
    <type>socks4</type>
    <anonymity>elite</anonymity>
</298>
<299>
    <country>Germany</country>
    <ip>5.189.129.137</ip>
    <port>8080</port>
    <type>socks4</type>
    <anonymity>elite</anonymity>
</299>
<300>
    <country>Brazil</country>
    <ip>45.7.177.200</ip>
    <port>39867</port>
    <type>socks4</type>
    <anonymity>elite</anonymity>
</300>
<301>
    <country>United States of America</country>
    <ip>203.24.109.109</ip>
    <port>80</port>
    <type>socks4</type>
    <anonymity>elite</anonymity>
</301>
<302>
    <country>Korea, Republic of</country>
    <ip>119.197.0.17</ip>
    <port>4145</port>
    <type>socks4</type>
    <anonymity>elite</anonymity>
</302>
<303>
    <country>Mexico</country>
    <ip>189.186.222.250</ip>
    <port>999</port>
    <type>socks4</type>
    <anonymity>elite</anonymity>
</303>
<304>
    <country>Russian Federation</country>
    <ip>158.58.133.38</ip>
    <port>5678</port>
    <type>socks4</type>
    <anonymity>elite</anonymity>
</304>
<305>
    <country>Germany</country>
    <ip>5.9.151.189</ip>
    <port>30000</port>
    <type>socks4</type>
    <anonymity>elite</anonymity>
</305>
<306>
    <country>Indonesia</country>
    <ip>103.85.67.114</ip>
    <port>4145</port>
    <type>socks4</type>
    <anonymity>elite</anonymity>
</306>
<307>
    <country>Indonesia</country>
    <ip>103.107.68.13</ip>
    <port>5430</port>
    <type>socks4</type>
    <anonymity>elite</anonymity>
</307>
<308>
    <country>Indonesia</country>
    <ip>36.90.168.64</ip>
    <port>51327</port>
    <type>socks4</type>
    <anonymity>elite</anonymity>
</308>
<309>
    <country>India</country>
    <ip>103.240.33.225</ip>
    <port>8291</port>
    <type>socks4</type>
    <anonymity>elite</anonymity>
</309>
<310>
    <country>India</country>
    <ip>103.47.93.247</ip>
    <port>1080</port>
    <type>socks4</type>
    <anonymity>elite</anonymity>
</310>
<311>
    <country>Poland</country>
    <ip>46.174.235.37</ip>
    <port>5678</port>
    <type>socks4</type>
    <anonymity>elite</anonymity>
</311>
<312>
    <country>Indonesia</country>
    <ip>103.135.225.205</ip>
    <port>4153</port>
    <type>socks4</type>
    <anonymity>elite</anonymity>
</312>
<313>
    <country>Cambodia</country>
    <ip>202.124.33.165</ip>
    <port>5678</port>
    <type>socks4</type>
    <anonymity>elite</anonymity>
</313>
<314>
    <country>India</country>
    <ip>117.241.132.95</ip>
    <port>5678</port>
    <type>socks4</type>
    <anonymity>elite</anonymity>
</314>
<315>
    <country>Czechia</country>
    <ip>185.94.6.178</ip>
    <port>4145</port>
    <type>socks4</type>
    <anonymity>elite</anonymity>
</315>
<316>
    <country>Mexico</country>
    <ip>189.201.191.20</ip>
    <port>4145</port>
    <type>socks4</type>
    <anonymity>elite</anonymity>
</316>
<317>
    <country>Czechia</country>
    <ip>5.181.93.127</ip>
    <port>4153</port>
    <type>socks4</type>
    <anonymity>elite</anonymity>
</317>
<318>
    <country>Germany</country>
    <ip>173.249.2.186</ip>
    <port>45708</port>
    <type>socks4</type>
    <anonymity>elite</anonymity>
</318>
<319>
    <country>Indonesia</country>
    <ip>27.123.1.37</ip>
    <port>4153</port>
    <type>socks4</type>
    <anonymity>elite</anonymity>
</319>
<320>
    <country>Georgia</country>
    <ip>78.40.104.5</ip>
    <port>1080</port>
    <type>socks4</type>
    <anonymity>elite</anonymity>
</320>
<321>
    <country>United States of America</country>
    <ip>103.83.36.1</ip>
    <port>5678</port>
    <type>socks4</type>
    <anonymity>elite</anonymity>
</321>
<322>
    <country>Bangladesh</country>
    <ip>103.116.118.10</ip>
    <port>4145</port>
    <type>socks4</type>
    <anonymity>elite</anonymity>
</322>
<323>
    <country>Brazil</country>
    <ip>177.136.213.79</ip>
    <port>4145</port>
    <type>socks4</type>
    <anonymity>elite</anonymity>
</323>
<324>
    <country>Poland</country>
    <ip>91.198.137.31</ip>
    <port>3509</port>
    <type>socks4</type>
    <anonymity>elite</anonymity>
</324>
<325>
    <country>Ukraine</country>
    <ip>91.224.179.175</ip>
    <port>5678</port>
    <type>socks4</type>
    <anonymity>elite</anonymity>
</325>
<326>
    <country>United States of America</country>
    <ip>104.25.58.39</ip>
    <port>80</port>
    <type>socks4</type>
    <anonymity>elite</anonymity>
</326>
<327>
    <country>China</country>
    <ip>58.18.43.34</ip>
    <port>10800</port>
    <type>socks4</type>
    <anonymity>elite</anonymity>
</327>
<328>
    <country>India</country>
    <ip>103.70.206.65</ip>
    <port>59311</port>
    <type>socks4</type>
    <anonymity>elite</anonymity>
</328>
<329>
    <country>United States of America</country>
    <ip>50.96.204.3</ip>
    <port>18351</port>
    <type>socks4</type>
    <anonymity>elite</anonymity>
</329>
<330>
    <country>India</country>
    <ip>103.251.221.57</ip>
    <port>4145</port>
    <type>socks4</type>
    <anonymity>elite</anonymity>
</330>
<331>
    <country>Seychelles</country>
    <ip>197.234.13.27</ip>
    <port>4145</port>
    <type>socks4</type>
    <anonymity>elite</anonymity>
</331>
<332>
    <country>Brazil</country>
    <ip>45.7.177.181</ip>
    <port>39867</port>
    <type>socks4</type>
    <anonymity>elite</anonymity>
</332>
<333>
    <country>Indonesia</country>
    <ip>36.89.218.67</ip>
    <port>1080</port>
    <type>socks4</type>
    <anonymity>elite</anonymity>
</333>
<334>
    <country>Indonesia</country>
    <ip>36.66.192.35</ip>
    <port>38420</port>
    <type>socks4</type>
    <anonymity>elite</anonymity>
</334>
<335>
    <country>Brazil</country>
    <ip>45.7.177.177</ip>
    <port>39867</port>
    <type>socks4</type>
    <anonymity>elite</anonymity>
</335>
<336>
    <country>Cambodia</country>
    <ip>110.74.208.153</ip>
    <port>21776</port>
    <type>socks4</type>
    <anonymity>elite</anonymity>
</336>
<337>
    <country>France</country>
    <ip>5.135.178.153</ip>
    <port>26506</port>
    <type>socks4</type>
    <anonymity>elite</anonymity>
</337>
<338>
    <country>United States of America</country>
    <ip>51.81.31.169</ip>
    <port>4485</port>
    <type>socks4</type>
    <anonymity>elite</anonymity>
</338>
<339>
    <country>Nepal</country>
    <ip>124.41.211.180</ip>
    <port>50405</port>
    <type>socks4</type>
    <anonymity>elite</anonymity>
</339>
<340>
    <country>Peru</country>
    <ip>181.65.121.34</ip>
    <port>8080</port>
    <type>socks4</type>
    <anonymity>elite</anonymity>
</340>
<341>
    <country>Italy</country>
    <ip>196.196.160.211</ip>
    <port>80</port>
    <type>socks4</type>
    <anonymity>elite</anonymity>
</341>
<342>
    <country>India</country>
    <ip>103.70.159.132</ip>
    <port>5678</port>
    <type>socks4</type>
    <anonymity>elite</anonymity>
</342>
<343>
    <country>Hong Kong</country>
    <ip>8.210.62.161</ip>
    <port>10020</port>
    <type>socks4</type>
    <anonymity>elite</anonymity>
</343>
<344>
    <country>Argentina</country>
    <ip>138.36.150.13</ip>
    <port>1080</port>
    <type>socks4</type>
    <anonymity>elite</anonymity>
</344>
<345>
    <country>Brazil</country>
    <ip>168.227.158.29</ip>
    <port>4145</port>
    <type>socks4</type>
    <anonymity>elite</anonymity>
</345>
<346>
    <country>Germany</country>
    <ip>195.93.200.140</ip>
    <port>80</port>
    <type>socks4</type>
    <anonymity>elite</anonymity>
</346>
<347>
    <country>Poland</country>
    <ip>178.212.52.198</ip>
    <port>1080</port>
    <type>socks4</type>
    <anonymity>elite</anonymity>
</347>
<348>
    <country>Italy</country>
    <ip>176.115.172.42</ip>
    <port>5678</port>
    <type>socks4</type>
    <anonymity>elite</anonymity>
</348>
<349>
    <country>Nigeria</country>
    <ip>41.76.86.202</ip>
    <port>5678</port>
    <type>socks4</type>
    <anonymity>elite</anonymity>
</349>
<350>
    <country>United States of America</country>
    <ip>35.244.232.197</ip>
    <port>80</port>
    <type>socks4</type>
    <anonymity>elite</anonymity>
</350>
<351>
    <country>Bangladesh</country>
    <ip>119.148.45.185</ip>
    <port>1088</port>
    <type>socks4</type>
    <anonymity>elite</anonymity>
</351>
<352>
    <country>Czechia</country>
    <ip>109.238.223.1</ip>
    <port>51372</port>
    <type>socks4</type>
    <anonymity>elite</anonymity>
</352>
<353>
    <country>Moldova, Republic of</country>
    <ip>188.138.139.216</ip>
    <port>4145</port>
    <type>socks4</type>
    <anonymity>elite</anonymity>
</353>
<354>
    <country>Brazil</country>
    <ip>177.86.64.1</ip>
    <port>3629</port>
    <type>socks4</type>
    <anonymity>elite</anonymity>
</354>
<355>
    <country>Singapore</country>
    <ip>180.87.170.21</ip>
    <port>1080</port>
    <type>socks4</type>
    <anonymity>elite</anonymity>
</355>
<356>
    <country>Singapore</country>
    <ip>128.199.175.145</ip>
    <port>443</port>
    <type>socks4</type>
    <anonymity>elite</anonymity>
</356>
<357>
    <country>Pakistan</country>
    <ip>202.166.164.115</ip>
    <port>5678</port>
    <type>socks4</type>
    <anonymity>elite</anonymity>
</357>
<358>
    <country>India</country>
    <ip>103.70.159.158</ip>
    <port>5678</port>
    <type>socks4</type>
    <anonymity>elite</anonymity>
</358>
<359>
    <country>United States of America</country>
    <ip>149.20.253.108</ip>
    <port>12551</port>
    <type>socks4</type>
    <anonymity>elite</anonymity>
</359>
<360>
    <country>India</country>
    <ip>103.81.13.201</ip>
    <port>44832</port>
    <type>socks4</type>
    <anonymity>elite</anonymity>
</360>
<361>
    <country>Botswana</country>
    <ip>41.79.138.85</ip>
    <port>5678</port>
    <type>socks4</type>
    <anonymity>elite</anonymity>
</361>
<362>
    <country>Thailand</country>
    <ip>110.78.151.213</ip>
    <port>4145</port>
    <type>socks4</type>
    <anonymity>elite</anonymity>
</362>
<363>
    <country>Russian Federation</country>
    <ip>193.34.161.129</ip>
    <port>44436</port>
    <type>socks4</type>
    <anonymity>elite</anonymity>
</363>
<364>
    <country>Brazil</country>
    <ip>186.251.255.61</ip>
    <port>31337</port>
    <type>socks4</type>
    <anonymity>elite</anonymity>
</364>
<365>
    <country>Poland</country>
    <ip>37.131.164.103</ip>
    <port>59341</port>
    <type>socks4</type>
    <anonymity>elite</anonymity>
</365>
<366>
    <country>Spain</country>
    <ip>185.161.186.84</ip>
    <port>54321</port>
    <type>socks4</type>
    <anonymity>elite</anonymity>
</366>
<367>
    <country>Poland</country>
    <ip>5.172.188.93</ip>
    <port>5678</port>
    <type>socks4</type>
    <anonymity>elite</anonymity>
</367>
<368>
    <country>United States of America</country>
    <ip>88.218.104.159</ip>
    <port>22272</port>
    <type>socks4</type>
    <anonymity>elite</anonymity>
</368>
<369>
    <country>India</country>
    <ip>45.126.169.185</ip>
    <port>4145</port>
    <type>socks4</type>
    <anonymity>elite</anonymity>
</369>
<370>
    <country>United States of America</country>
    <ip>198.211.23.213</ip>
    <port>30001</port>
    <type>socks4</type>
    <anonymity>elite</anonymity>
</370>