<0>
    <ip>209.126.9.164</ip>
    <port>27651</port>
    <country>United States of America</country>
    <type>socks4</type>
    <anonymity>High</anonymity>
</0>
<1>
    <ip>107.152.98.5</ip>
    <port>4145</port>
    <country>United States of America</country>
    <type>socks4</type>
    <anonymity>High</anonymity>
</1>
<2>
    <ip>209.126.9.164</ip>
    <port>27651</port>
    <country>United States of America</country>
    <type>socks4</type>
    <anonymity>High</anonymity>
</2>
<3>
    <ip>107.152.98.5</ip>
    <port>4145</port>
    <country>United States of America</country>
    <type>socks4</type>
    <anonymity>High</anonymity>
</3>
<4>
    <ip>184.181.217.210</ip>
    <port>4145</port>
    <country>United States of America</country>
    <type>socks4</type>
    <anonymity>High</anonymity>
</4>
<5>
    <ip>167.99.5.52</ip>
    <port>59919</port>
    <country>United States of America</country>
    <type>socks4</type>
    <anonymity>High</anonymity>
</5>
<6>
    <ip>70.35.199.99</ip>
    <port>56633</port>
    <country>United States of America</country>
    <type>socks4</type>
    <anonymity>High</anonymity>
</6>
<7>
    <ip>51.79.85.230</ip>
    <port>42537</port>
    <country>Canada</country>
    <type>socks4</type>
    <anonymity>High</anonymity>
</7>
<8>
    <ip>5.161.183.125</ip>
    <port>57573</port>
    <country>Germany</country>
    <type>socks4</type>
    <anonymity>High</anonymity>
</8>
<9>
    <ip>185.32.189.189</ip>
    <port>59679</port>
    <country>Portugal</country>
    <type>socks4</type>
    <anonymity>High</anonymity>
</9>
<10>
    <ip>103.142.26.23</ip>
    <port>2982</port>
    <country>Viet Nam</country>
    <type>socks4</type>
    <anonymity>High</anonymity>
</10>
<11>
    <ip>147.182.211.202</ip>
    <port>34187</port>
    <country>United States of America</country>
    <type>socks4</type>
    <anonymity>High</anonymity>
</11>
<12>
    <ip>47.254.153.78</ip>
    <port>8024</port>
    <country>China</country>
    <type>socks4</type>
    <anonymity>High</anonymity>
</12>
<13>
    <ip>199.102.107.145</ip>
    <port>4145</port>
    <country>United States of America</country>
    <type>socks4</type>
    <anonymity>High</anonymity>
</13>
<14>
    <ip>47.91.56.120</ip>
    <port>8083</port>
    <country>China</country>
    <type>socks4</type>
    <anonymity>High</anonymity>
</14>
<15>
    <ip>162.144.74.156</ip>
    <port>3620</port>
    <country>United States of America</country>
    <type>socks4</type>
    <anonymity>High</anonymity>
</15>
<16>
    <ip>142.54.237.34</ip>
    <port>4145</port>
    <country>United States of America</country>
    <type>socks4</type>
    <anonymity>High</anonymity>
</16>
<17>
    <ip>70.35.199.99</ip>
    <port>53984</port>
    <country>United States of America</country>
    <type>socks4</type>
    <anonymity>High</anonymity>
</17>
<18>
    <ip>184.170.245.148</ip>
    <port>4145</port>
    <country>United States of America</country>
    <type>socks4</type>
    <anonymity>High</anonymity>
</18>
<19>
    <ip>54.38.176.200</ip>
    <port>58346</port>
    <country>France</country>
    <type>socks4</type>
    <anonymity>High</anonymity>
</19>
<20>
    <ip>5.42.87.164</ip>
    <port>56789</port>
    <country>Russian Federation</country>
    <type>socks4</type>
    <anonymity>High</anonymity>
</20>
<21>
    <ip>134.209.36.143</ip>
    <port>10026</port>
    <country>United States of America</country>
    <type>socks4</type>
    <anonymity>High</anonymity>
</21>
<22>
    <ip>45.11.93.77</ip>
    <port>57312</port>
    <country>Russian Federation</country>
    <type>socks4</type>
    <anonymity>High</anonymity>
</22>
<23>
    <ip>143.198.229.56</ip>
    <port>12914</port>
    <country>United States of America</country>
    <type>socks4</type>
    <anonymity>High</anonymity>
</23>
<24>
    <ip>107.181.168.145</ip>
    <port>4145</port>
    <country>United States of America</country>
    <type>socks4</type>
    <anonymity>High</anonymity>
</24>
<25>
    <ip>72.37.217.3</ip>
    <port>4145</port>
    <country>United States of America</country>
    <type>socks4</type>
    <anonymity>High</anonymity>
</25>
<26>
    <ip>74.119.144.60</ip>
    <port>4145</port>
    <country>United States of America</country>
    <type>socks4</type>
    <anonymity>High</anonymity>
</26>
<27>
    <ip>203.57.51.200</ip>
    <port>57827</port>
    <country>Australia</country>
    <type>socks4</type>
    <anonymity>High</anonymity>
</27>
<28>
    <ip>184.178.172.5</ip>
    <port>15303</port>
    <country>United States of America</country>
    <type>socks4</type>
    <anonymity>High</anonymity>
</28>
<29>
    <ip>72.206.181.123</ip>
    <port>4145</port>
    <country>United States of America</country>
    <type>socks4</type>
    <anonymity>High</anonymity>
</29>
<30>
    <ip>72.206.181.97</ip>
    <port>64943</port>
    <country>United States of America</country>
    <type>socks4</type>
    <anonymity>High</anonymity>
</30>
<31>
    <ip>184.178.172.28</ip>
    <port>15294</port>
    <country>United States of America</country>
    <type>socks4</type>
    <anonymity>High</anonymity>
</31>
<32>
    <ip>98.162.25.7</ip>
    <port>31653</port>
    <country>United States of America</country>
    <type>socks4</type>
    <anonymity>High</anonymity>
</32>
<33>
    <ip>98.162.25.4</ip>
    <port>31654</port>
    <country>United States of America</country>
    <type>socks4</type>
    <anonymity>High</anonymity>
</33>
<34>
    <ip>72.206.181.105</ip>
    <port>64935</port>
    <country>United States of America</country>
    <type>socks4</type>
    <anonymity>High</anonymity>
</34>
<35>
    <ip>174.64.199.82</ip>
    <port>4145</port>
    <country>United States of America</country>
    <type>socks4</type>
    <anonymity>High</anonymity>
</35>
<36>
    <ip>68.183.16.227</ip>
    <port>55354</port>
    <country>United States of America</country>
    <type>socks4</type>
    <anonymity>High</anonymity>
</36>
<37>
    <ip>68.1.210.163</ip>
    <port>4145</port>
    <country>United States of America</country>
    <type>socks4</type>
    <anonymity>High</anonymity>
</37>
<38>
    <ip>157.230.1.108</ip>
    <port>14070</port>
    <country>United States of America</country>
    <type>socks4</type>
    <anonymity>High</anonymity>
</38>
<39>
    <ip>70.35.199.99</ip>
    <port>50420</port>
    <country>United States of America</country>
    <type>socks4</type>
    <anonymity>High</anonymity>
</39>
<40>
    <ip>104.200.135.46</ip>
    <port>4145</port>
    <country>United States of America</country>
    <type>socks4</type>
    <anonymity>High</anonymity>
</40>
<41>
    <ip>8.219.67.223</ip>
    <port>26688</port>
    <country>Singapore</country>
    <type>socks4</type>
    <anonymity>High</anonymity>
</41>
<42>
    <ip>138.68.16.30</ip>
    <port>13469</port>
    <country>United States of America</country>
    <type>socks4</type>
    <anonymity>High</anonymity>
</42>
<43>
    <ip>202.86.138.18</ip>
    <port>8080</port>
    <country>Macao</country>
    <type>socks4</type>
    <anonymity>High</anonymity>
</43>
<44>
    <ip>5.161.131.42</ip>
    <port>56191</port>
    <country>Germany</country>
    <type>socks4</type>
    <anonymity>High</anonymity>
</44>
<45>
    <ip>98.162.25.29</ip>
    <port>31679</port>
    <country>United States of America</country>
    <type>socks4</type>
    <anonymity>High</anonymity>
</45>
<46>
    <ip>174.64.199.79</ip>
    <port>4145</port>
    <country>United States of America</country>
    <type>socks4</type>
    <anonymity>High</anonymity>
</46>
<47>
    <ip>72.195.34.58</ip>
    <port>4145</port>
    <country>United States of America</country>
    <type>socks4</type>
    <anonymity>High</anonymity>
</47>
<48>
    <ip>194.233.78.142</ip>
    <port>49653</port>
    <country>Germany</country>
    <type>socks4</type>
    <anonymity>High</anonymity>
</48>
<49>
    <ip>130.255.165.131</ip>
    <port>55605</port>
    <country>Sweden</country>
    <type>socks4</type>
    <anonymity>High</anonymity>
</49>
<50>
    <ip>184.170.248.5</ip>
    <port>4145</port>
    <country>United States of America</country>
    <type>socks4</type>
    <anonymity>High</anonymity>
</50>
<51>
    <ip>72.210.208.101</ip>
    <port>4145</port>
    <country>United States of America</country>
    <type>socks4</type>
    <anonymity>High</anonymity>
</51>
<52>
    <ip>199.229.254.129</ip>
    <port>4145</port>
    <country>United States of America</country>
    <type>socks4</type>
    <anonymity>High</anonymity>
</52>
<53>
    <ip>72.210.252.137</ip>
    <port>4145</port>
    <country>United States of America</country>
    <type>socks4</type>
    <anonymity>High</anonymity>
</53>
<54>
    <ip>72.210.221.223</ip>
    <port>4145</port>
    <country>United States of America</country>
    <type>socks4</type>
    <anonymity>High</anonymity>
</54>
<55>
    <ip>68.1.210.189</ip>
    <port>4145</port>
    <country>United States of America</country>
    <type>socks4</type>
    <anonymity>High</anonymity>
</55>
<56>
    <ip>157.245.139.82</ip>
    <port>28427</port>
    <country>United States of America</country>
    <type>socks4</type>
    <anonymity>High</anonymity>
</56>
<57>
    <ip>167.71.250.32</ip>
    <port>6502</port>
    <country>United States of America</country>
    <type>socks4</type>
    <anonymity>High</anonymity>
</57>
<58>
    <ip>131.186.37.99</ip>
    <port>8080</port>
    <country>United States of America</country>
    <type>socks4</type>
    <anonymity>High</anonymity>
</58>
<59>
    <ip>203.57.51.200</ip>
    <port>23373</port>
    <country>Australia</country>
    <type>socks4</type>
    <anonymity>High</anonymity>
</59>
<60>
    <ip>72.195.34.41</ip>
    <port>4145</port>
    <country>United States of America</country>
    <type>socks4</type>
    <anonymity>High</anonymity>
</60>
<61>
    <ip>98.170.57.249</ip>
    <port>4145</port>
    <country>United States of America</country>
    <type>socks4</type>
    <anonymity>High</anonymity>
</61>
<62>
    <ip>184.178.172.18</ip>
    <port>15280</port>
    <country>United States of America</country>
    <type>socks4</type>
    <anonymity>High</anonymity>
</62>
<63>
    <ip>184.181.217.220</ip>
    <port>4145</port>
    <country>United States of America</country>
    <type>socks4</type>
    <anonymity>High</anonymity>
</63>
<64>
    <ip>184.178.172.25</ip>
    <port>15291</port>
    <country>United States of America</country>
    <type>socks4</type>
    <anonymity>High</anonymity>
</64>
<65>
    <ip>43.154.107.138</ip>
    <port>3001</port>
    <country>Japan</country>
    <type>socks4</type>
    <anonymity>High</anonymity>
</65>
<66>
    <ip>98.175.31.195</ip>
    <port>4145</port>
    <country>United States of America</country>
    <type>socks4</type>
    <anonymity>High</anonymity>
</66>
<67>
    <ip>67.201.33.10</ip>
    <port>25283</port>
    <country>United States of America</country>
    <type>socks4</type>
    <anonymity>High</anonymity>
</67>
<68>
    <ip>70.166.167.55</ip>
    <port>57745</port>
    <country>United States of America</country>
    <type>socks4</type>
    <anonymity>High</anonymity>
</68>
<69>
    <ip>65.169.38.73</ip>
    <port>26592</port>
    <country>United States of America</country>
    <type>socks4</type>
    <anonymity>High</anonymity>
</69>
<70>
    <ip>72.210.221.197</ip>
    <port>4145</port>
    <country>United States of America</country>
    <type>socks4</type>
    <anonymity>High</anonymity>
</70>
<71>
    <ip>184.185.2.12</ip>
    <port>4145</port>
    <country>United States of America</country>
    <type>socks4</type>
    <anonymity>High</anonymity>
</71>
<72>
    <ip>174.77.111.197</ip>
    <port>4145</port>
    <country>United States of America</country>
    <type>socks4</type>
    <anonymity>High</anonymity>
</72>
<73>
    <ip>157.245.139.82</ip>
    <port>49502</port>
    <country>United States of America</country>
    <type>socks4</type>
    <anonymity>High</anonymity>
</73>
<74>
    <ip>143.198.229.56</ip>
    <port>58409</port>
    <country>United States of America</country>
    <type>socks4</type>
    <anonymity>High</anonymity>
</74>
<75>
    <ip>72.195.34.35</ip>
    <port>27360</port>
    <country>United States of America</country>
    <type>socks4</type>
    <anonymity>High</anonymity>
</75>
<76>
    <ip>68.71.249.153</ip>
    <port>48606</port>
    <country>United States of America</country>
    <type>socks4</type>
    <anonymity>High</anonymity>
</76>
<77>
    <ip>98.188.47.150</ip>
    <port>4145</port>
    <country>United States of America</country>
    <type>socks4</type>
    <anonymity>High</anonymity>
</77>
<78>
    <ip>70.166.167.38</ip>
    <port>57728</port>
    <country>United States of America</country>
    <type>socks4</type>
    <anonymity>High</anonymity>
</78>
<79>
    <ip>142.54.226.214</ip>
    <port>4145</port>
    <country>United States of America</country>
    <type>socks4</type>
    <anonymity>High</anonymity>
</79>
<80>
    <ip>72.195.34.60</ip>
    <port>27391</port>
    <country>United States of America</country>
    <type>socks4</type>
    <anonymity>High</anonymity>
</80>
<81>
    <ip>64.227.108.25</ip>
    <port>31908</port>
    <country>United States of America</country>
    <type>socks4</type>
    <anonymity>High</anonymity>
</81>
<82>
    <ip>51.15.212.207</ip>
    <port>16379</port>
    <country>France</country>
    <type>socks4</type>
    <anonymity>High</anonymity>
</82>
<83>
    <ip>70.35.199.99</ip>
    <port>56282</port>
    <country>United States of America</country>
    <type>socks4</type>
    <anonymity>High</anonymity>
</83>
<84>
    <ip>199.116.114.11</ip>
    <port>4145</port>
    <country>United States of America</country>
    <type>socks4</type>
    <anonymity>High</anonymity>
</84>
<85>
    <ip>79.137.34.146</ip>
    <port>50841</port>
    <country>France</country>
    <type>socks4</type>
    <anonymity>High</anonymity>
</85>
<86>
    <ip>167.71.250.32</ip>
    <port>43965</port>
    <country>United States of America</country>
    <type>socks4</type>
    <anonymity>High</anonymity>
</86>
<87>
    <ip>54.36.122.141</ip>
    <port>14174</port>
    <country>France</country>
    <type>socks4</type>
    <anonymity>High</anonymity>
</87>
<88>
    <ip>194.233.78.142</ip>
    <port>35314</port>
    <country>Germany</country>
    <type>socks4</type>
    <anonymity>High</anonymity>
</88>
<89>
    <ip>208.113.160.4</ip>
    <port>29780</port>
    <country>United States of America</country>
    <type>socks4</type>
    <anonymity>High</anonymity>
</89>
<90>
    <ip>138.68.6.162</ip>
    <port>33835</port>
    <country>United States of America</country>
    <type>socks4</type>
    <anonymity>High</anonymity>
</90>
<91>
    <ip>138.68.6.162</ip>
    <port>33835</port>
    <country>United States of America</country>
    <type>socks4</type>
    <anonymity>High</anonymity>
</91>
<92>
    <ip>143.198.151.113</ip>
    <port>34005</port>
    <country>United States of America</country>
    <type>socks4</type>
    <anonymity>High</anonymity>
</92>
<93>
    <ip>167.71.241.237</ip>
    <port>63838</port>
    <country>United States of America</country>
    <type>socks4</type>
    <anonymity>High</anonymity>
</93>
<94>
    <ip>163.172.161.35</ip>
    <port>16379</port>
    <country>France</country>
    <type>socks4</type>
    <anonymity>High</anonymity>
</94>
<95>
    <ip>167.99.114.17</ip>
    <port>3129</port>
    <country>United States of America</country>
    <type>socks4</type>
    <anonymity>High</anonymity>
</95>
<96>
    <ip>198.11.175.192</ip>
    <port>5000</port>
    <country>United States of America</country>
    <type>socks4</type>
    <anonymity>High</anonymity>
</96>
<97>
    <ip>192.99.201.39</ip>
    <port>64763</port>
    <country>Canada</country>
    <type>socks4</type>
    <anonymity>High</anonymity>
</97>
<98>
    <ip>69.163.161.0</ip>
    <port>53468</port>
    <country>United States of America</country>
    <type>socks4</type>
    <anonymity>High</anonymity>
</98>
<99>
    <ip>103.30.201.39</ip>
    <port>3001</port>
    <country>China</country>
    <type>socks4</type>
    <anonymity>High</anonymity>
</99>
<100>
    <ip>51.222.241.8</ip>
    <port>2464</port>
    <country>France</country>
    <type>socks4</type>
    <anonymity>High</anonymity>
</100>
<101>
    <ip>130.255.165.184</ip>
    <port>6810</port>
    <country>Sweden</country>
    <type>socks4</type>
    <anonymity>High</anonymity>
</101>
<102>
    <ip>173.212.245.45</ip>
    <port>3232</port>
    <country>Germany</country>
    <type>socks4</type>
    <anonymity>High</anonymity>
</102>
<103>
    <ip>51.15.254.129</ip>
    <port>16379</port>
    <country>France</country>
    <type>socks4</type>
    <anonymity>High</anonymity>
</103>
<104>
    <ip>47.250.144.79</ip>
    <port>1666</port>
    <country>United States of America</country>
    <type>socks4</type>
    <anonymity>High</anonymity>
</104>
<105>
    <ip>166.88.35.19</ip>
    <port>11098</port>
    <country>United States of America</country>
    <type>socks4</type>
    <anonymity>High</anonymity>
</105>
<106>
    <ip>70.35.199.99</ip>
    <port>59648</port>
    <country>United States of America</country>
    <type>socks4</type>
    <anonymity>High</anonymity>
</106>
<107>
    <ip>68.183.16.227</ip>
    <port>29150</port>
    <country>United States of America</country>
    <type>socks4</type>
    <anonymity>High</anonymity>
</107>
<108>
    <ip>167.71.241.136</ip>
    <port>33299</port>
    <country>United States of America</country>
    <type>socks4</type>
    <anonymity>High</anonymity>
</108>
<109>
    <ip>208.113.196.67</ip>
    <port>32421</port>
    <country>United States of America</country>
    <type>socks4</type>
    <anonymity>High</anonymity>
</109>
<110>
    <ip>103.38.102.243</ip>
    <port>5678</port>
    <country>Indonesia</country>
    <type>socks4</type>
    <anonymity>High</anonymity>
</110>
<111>
    <ip>147.182.211.202</ip>
    <port>52134</port>
    <country>United States of America</country>
    <type>socks4</type>
    <anonymity>High</anonymity>
</111>
<112>
    <ip>159.69.82.209</ip>
    <port>28326</port>
    <country>Germany</country>
    <type>socks4</type>
    <anonymity>High</anonymity>
</112>
<113>
    <ip>45.79.25.205</ip>
    <port>30448</port>
    <country>United States of America</country>
    <type>socks4</type>
    <anonymity>High</anonymity>
</113>
<114>
    <ip>185.82.126.227</ip>
    <port>8590</port>
    <country>Sweden</country>
    <type>socks4</type>
    <anonymity>High</anonymity>
</114>
<115>
    <ip>45.32.172.135</ip>
    <port>8083</port>
    <country>United States of America</country>
    <type>socks4</type>
    <anonymity>High</anonymity>
</115>
<116>
    <ip>8.209.253.237</ip>
    <port>8192</port>
    <country>Singapore</country>
    <type>socks4</type>
    <anonymity>High</anonymity>
</116>
<117>
    <ip>38.242.244.63</ip>
    <port>24769</port>
    <country>United States of America</country>
    <type>socks4</type>
    <anonymity>High</anonymity>
</117>
<118>
    <ip>209.126.127.72</ip>
    <port>55354</port>
    <country>United States of America</country>
    <type>socks4</type>
    <anonymity>High</anonymity>
</118>
<119>
    <ip>125.141.133.98</ip>
    <port>5566</port>
    <country>Korea (Republic of)</country>
    <type>socks4</type>
    <anonymity>High</anonymity>
</119>
<120>
    <ip>167.71.250.32</ip>
    <port>10358</port>
    <country>United States of America</country>
    <type>socks4</type>
    <anonymity>High</anonymity>
</120>
<121>
    <ip>132.148.75.242</ip>
    <port>27087</port>
    <country>United States of America</country>
    <type>socks4</type>
    <anonymity>High</anonymity>
</121>
<122>
    <ip>138.68.6.162</ip>
    <port>21919</port>
    <country>United States of America</country>
    <type>socks4</type>
    <anonymity>High</anonymity>
</122>
<123>
    <ip>138.68.240.214</ip>
    <port>57914</port>
    <country>United States of America</country>
    <type>socks4</type>
    <anonymity>High</anonymity>
</123>
<124>
    <ip>194.233.78.142</ip>
    <port>41215</port>
    <country>Germany</country>
    <type>socks4</type>
    <anonymity>High</anonymity>
</124>
<125>
    <ip>43.135.159.216</ip>
    <port>12316</port>
    <country>Japan</country>
    <type>socks4</type>
    <anonymity>High</anonymity>
</125>
<126>
    <ip>207.180.228.214</ip>
    <port>25383</port>
    <country>Germany</country>
    <type>socks4</type>
    <anonymity>High</anonymity>
</126>
<127>
    <ip>163.172.147.89</ip>
    <port>16379</port>
    <country>France</country>
    <type>socks4</type>
    <anonymity>High</anonymity>
</127>
<128>
    <ip>38.242.244.63</ip>
    <port>23553</port>
    <country>United States of America</country>
    <type>socks4</type>
    <anonymity>High</anonymity>
</128>
<129>
    <ip>69.61.200.104</ip>
    <port>36181</port>
    <country>United States of America</country>
    <type>socks4</type>
    <anonymity>High</anonymity>
</129>
<130>
    <ip>5.133.195.196</ip>
    <port>41156</port>
    <country>Sweden</country>
    <type>socks4</type>
    <anonymity>High</anonymity>
</130>
<131>
    <ip>47.91.56.120</ip>
    <port>3132</port>
    <country>China</country>
    <type>socks4</type>
    <anonymity>High</anonymity>
</131>
<132>
    <ip>208.113.186.40</ip>
    <port>27876</port>
    <country>United States of America</country>
    <type>socks4</type>
    <anonymity>High</anonymity>
</132>
<133>
    <ip>218.78.21.165</ip>
    <port>7750</port>
    <country>China</country>
    <type>socks4</type>
    <anonymity>High</anonymity>
</133>
<134>
    <ip>37.187.91.192</ip>
    <port>27898</port>
    <country>France</country>
    <type>socks4</type>
    <anonymity>High</anonymity>
</134>
<135>
    <ip>167.71.250.32</ip>
    <port>45209</port>
    <country>United States of America</country>
    <type>socks4</type>
    <anonymity>High</anonymity>
</135>
<136>
    <ip>144.91.95.238</ip>
    <port>58237</port>
    <country>Germany</country>
    <type>socks4</type>
    <anonymity>High</anonymity>
</136>
<137>
    <ip>5.161.183.125</ip>
    <port>64844</port>
    <country>Germany</country>
    <type>socks4</type>
    <anonymity>High</anonymity>
</137>